ademi/__init__.py
ademi/ademi.py
ademi-0.0.1.dist-info/LICENSE
ademi-0.0.1.dist-info/METADATA
ademi-0.0.1.dist-info/WHEEL
ademi-0.0.1.dist-info/top_level.txt
ademi-0.0.1.dist-info/RECORD
